undesirablereasons/__init__.py
undesirablereasons/main.py
undesirablereasons/prompts.py
undesirablereasons-2025.12.21151640.dist-info/METADATA
undesirablereasons-2025.12.21151640.dist-info/WHEEL
undesirablereasons-2025.12.21151640.dist-info/top_level.txt
undesirablereasons-2025.12.21151640.dist-info/RECORD
