Metadata-Version: 2.4
Name: undesirablereasons
Version: 2025.12.21151640
Summary: A new package that helps users extract and organize key reasons from text inputs, specifically focusing on why certain actions or outcomes might be undesirable. For example, given a text input about t
Author-email: undesirablereasons <hi@eugene.plus>
License: MIT
Project-URL: Homepage, https://github.com/chigwell/undesirablereasons
Requires-Python: >=3.9
Requires-Dist: langchain-llm7>=0.0.0
Requires-Dist: llmatch-messages>=0.0.0
Requires-Dist: langchain-core>=0.3.0
